inpynit/__init__.py
inpynit/__main__.py
inpynit/_version.py
inpynit/cli.py
inpynit/core.py
inpynit/templates.py
inpynit/utils.py
inpynit/templates/basic/Makefile.j2
inpynit/templates/basic/README.md.j2
inpynit/templates/basic/gitignore.j2
inpynit/templates/basic/main.py.j2
inpynit/templates/basic/pyproject.toml.j2
inpynit/templates/basic/test_main.py.j2
inpynit-0.0.5.dist-info/licenses/LICENSE
inpynit-0.0.5.dist-info/METADATA
inpynit-0.0.5.dist-info/WHEEL
inpynit-0.0.5.dist-info/entry_points.txt
inpynit-0.0.5.dist-info/top_level.txt
inpynit-0.0.5.dist-info/RECORD
