Metadata-Version: 2.4
Name: inpynit
Version: 0.0.5
Summary: 무한한 가능성을 가진 파이썬 프로젝트를 시작하게 해주는 도구
Author-email: Your Name <your.email@example.com>
License-Expression: MIT
Project-URL: Homepage, https://github.com/yourusername/inpynit
Project-URL: Repository, https://github.com/yourusername/inpynit
Project-URL: Documentation, https://inpynit.readthedocs.io
Project-URL: Bug Tracker, https://github.com/yourusername/inpynit/issues
Keywords: python,project,template,cli,init
Classifier: Development Status :: 3 - Alpha
Classifier: Intended Audience :: Developers
Classifier: Programming Language :: Python :: 3
Classifier: Programming Language :: Python :: 3.8
Classifier: Programming Language :: Python :: 3.9
Classifier: Programming Language :: Python :: 3.10
Classifier: Programming Language :: Python :: 3.11
Classifier: Programming Language :: Python :: 3.12
Requires-Python: >=3.8
License-File: LICENSE
Requires-Dist: click>=8.0.0
Requires-Dist: jinja2>=3.0.0
Requires-Dist: rich>=12.0.0
Requires-Dist: toml>=0.10.0
Provides-Extra: dev
Requires-Dist: pytest>=7.0.0; extra == "dev"
Requires-Dist: ruff>=0.1.0; extra == "dev"
Requires-Dist: build>=0.10.0; extra == "dev"
Requires-Dist: setuptools-scm>=6.2; extra == "dev"
Dynamic: license-file
